impscore/__init__.py
impscore/model.py
implicit_score-0.1.3.dist-info/METADATA
implicit_score-0.1.3.dist-info/WHEEL
implicit_score-0.1.3.dist-info/top_level.txt
implicit_score-0.1.3.dist-info/RECORD
