Metadata-Version: 2.2
Name: implicit-score
Version: 0.1.3
Summary: A learnable metric to calculate the implicitness of an English sentence
Home-page: https://github.com/audreycs/impscore
Author: Yuxin Wang
Author-email: yuxinwangcs@outlook.com
Classifier: Programming Language :: Python :: 3
Classifier: License :: OSI Approved :: MIT License
Classifier: Operating System :: OS Independent
Requires-Python: >=3.7
Requires-Dist: sentence-transformers
Requires-Dist: huggingface_hub
Requires-Dist: torch
Dynamic: author
Dynamic: author-email
Dynamic: classifier
Dynamic: description
Dynamic: description-content-type
Dynamic: home-page
Dynamic: requires-dist
Dynamic: requires-python
Dynamic: summary
